compath_hgnc/__init__.py
compath_hgnc/__main__.py
compath_hgnc/cli.py
compath_hgnc/manager.py
compath_hgnc-0.0.1.dist-info/METADATA
compath_hgnc-0.0.1.dist-info/RECORD
compath_hgnc-0.0.1.dist-info/WHEEL
compath_hgnc-0.0.1.dist-info/entry_points.txt
compath_hgnc-0.0.1.dist-info/top_level.txt
