Metadata-Version: 2.1
Name: compath-hgnc
Version: 0.0.1
Summary: A package that wraps PyHGNC to perform mappings between different gene identifiers
Home-page: https://github.com/ComPath/compath_hgnc
Author: Daniel Domingo Fernández
Author-email: daniel.domingo.fernandez@scai.fraunhofer.de
Maintainer: Daniel Domingo Fernández
Maintainer-email: daniel.domingo.fernandez@scai.fraunhofer.de
License: MIT License
Keywords: Pathways,Systems Biology,Networks Biology
Platform: UNKNOWN
Classifier: Development Status :: 4 - Beta
Classifier: Environment :: Console
Classifier: Intended Audience :: Developers
Classifier: Intended Audience :: Science/Research
Classifier: License :: OSI Approved :: MIT License
Classifier: Operating System :: OS Independent
Classifier: Programming Language :: Python
Classifier: Programming Language :: Python :: 3.4
Classifier: Programming Language :: Python :: 3.5
Classifier: Programming Language :: Python :: 3.6
Classifier: Topic :: Scientific/Engineering :: Bio-Informatics
Requires-Dist: pybel (>=0.10.1)
Requires-Dist: bio2bel (>=0.0.9)
Requires-Dist: compath-utils
Requires-Dist: bio2bel-hgnc
Requires-Dist: sqlalchemy
Requires-Dist: click
Requires-Dist: pandas
